duden_webscraper/__init__.py
duden_webscraper/duden_web_scraper.py
duden_webscraper/endpoint.py
duden_webscraper/py.typed
duden_webscraper/word_info_error.py
duden_webscraper/word_not_found_error.py
duden_webscraper-0.1.0.dist-info/WHEEL
duden_webscraper-0.1.0.dist-info/METADATA
duden_webscraper-0.1.0.dist-info/RECORD
